MANIFEST.in
README.rst
requirements.txt
setup.cfg
setup.py
sequana_pacbio_qc.egg-info/PKG-INFO
sequana_pacbio_qc.egg-info/SOURCES.txt
sequana_pacbio_qc.egg-info/dependency_links.txt
sequana_pacbio_qc.egg-info/entry_points.txt
sequana_pacbio_qc.egg-info/not-zip-safe
sequana_pacbio_qc.egg-info/requires.txt
sequana_pacbio_qc.egg-info/top_level.txt
sequana_pipelines/pacbio_qc/__init__.py
sequana_pipelines/pacbio_qc/config.yaml
sequana_pipelines/pacbio_qc/dag.png
sequana_pipelines/pacbio_qc/main.py
sequana_pipelines/pacbio_qc/multiqc_config.yaml
sequana_pipelines/pacbio_qc/pacbio_qc.rules
sequana_pipelines/pacbio_qc/requirements.txt
sequana_pipelines/pacbio_qc/schema.yaml